ldclient/__init__.py
ldclient-0.0.1.dist-info/LICENSE
ldclient-0.0.1.dist-info/METADATA
ldclient-0.0.1.dist-info/WHEEL
ldclient-0.0.1.dist-info/top_level.txt
ldclient-0.0.1.dist-info/RECORD
