Metadata-Version: 2.1
Name: ldclient
Version: 0.0.1
Summary: LiveDesign Client
Home-page: https://github.com/schrodinger/livedesign-client
Author: Andy Martin
Author-email: andy.martin@schrodinger.com
License: UNKNOWN
Platform: UNKNOWN
